bytes2wavbytes/__init__.py
bytes2wavbytes/py.typed
bytes2wavbytes/utils.py
bytes2wavbytes-0.1.1.dist-info/METADATA
bytes2wavbytes-0.1.1.dist-info/WHEEL
bytes2wavbytes-0.1.1.dist-info/RECORD
