Metadata-Version: 2.4
Name: bytes2wavbytes
Version: 0.1.1
Summary: Add your description here
Author-email: cpwan <cpwan@connect.ust.hk>
Requires-Python: >=3.10
Requires-Dist: python-magic>=0.4.27
